kymatio/__init__.py
kymatio/caching.py
kymatio/datasets.py
kymatio/jax.py
kymatio/keras.py
kymatio/numpy.py
kymatio/sklearn.py
kymatio/tensorflow.py
kymatio/torch.py
kymatio/version.py
kymatio/backend/__init__.py
kymatio/backend/jax_backend.py
kymatio/backend/numpy_backend.py
kymatio/backend/tensorflow_backend.py
kymatio/backend/torch_backend.py
kymatio/backend/torch_skcuda_backend.py
kymatio/frontend/__init__.py
kymatio/frontend/base_frontend.py
kymatio/frontend/entry.py
kymatio/frontend/jax_frontend.py
kymatio/frontend/keras_frontend.py
kymatio/frontend/numpy_frontend.py
kymatio/frontend/sklearn_frontend.py
kymatio/frontend/tensorflow_frontend.py
kymatio/frontend/torch_frontend.py
kymatio/scattering1d/__init__.py
kymatio/scattering1d/filter_bank.py
kymatio/scattering1d/utils.py
kymatio/scattering1d/backend/__init__.py
kymatio/scattering1d/backend/jax_backend.py
kymatio/scattering1d/backend/numpy_backend.py
kymatio/scattering1d/backend/tensorflow_backend.py
kymatio/scattering1d/backend/torch_backend.py
kymatio/scattering1d/backend/torch_skcuda_backend.py
kymatio/scattering1d/core/__init__.py
kymatio/scattering1d/core/scattering1d.py
kymatio/scattering1d/frontend/__init__.py
kymatio/scattering1d/frontend/base_frontend.py
kymatio/scattering1d/frontend/entry.py
kymatio/scattering1d/frontend/jax_frontend.py
kymatio/scattering1d/frontend/keras_frontend.py
kymatio/scattering1d/frontend/numpy_frontend.py
kymatio/scattering1d/frontend/sklearn_frontend.py
kymatio/scattering1d/frontend/tensorflow_frontend.py
kymatio/scattering1d/frontend/torch_frontend.py
kymatio/scattering2d/__init__.py
kymatio/scattering2d/filter_bank.py
kymatio/scattering2d/utils.py
kymatio/scattering2d/backend/__init__.py
kymatio/scattering2d/backend/jax_backend.py
kymatio/scattering2d/backend/numpy_backend.py
kymatio/scattering2d/backend/tensorflow_backend.py
kymatio/scattering2d/backend/torch_backend.py
kymatio/scattering2d/backend/torch_skcuda_backend.py
kymatio/scattering2d/core/__init__.py
kymatio-0.3.0.dist-info/AUTHORS.md
kymatio-0.3.0.dist-info/LICENSE.md
kymatio-0.3.0.dist-info/METADATA
kymatio-0.3.0.dist-info/WHEEL
kymatio-0.3.0.dist-info/top_level.txt
kymatio-0.3.0.dist-info/zip-safe
kymatio-0.3.0.dist-info/RECORD
