Metadata-Version: 2.1
Name: kymatio
Version: 0.3.0
Summary: Wavelet scattering transforms in Python with GPU acceleration
Home-page: https://www.kymat.io
Author: Edouard Oyallon, Eugene Belilovsky, Sergey Zagoruyko, Michael Eickenberg, Mathieu Andreux, Georgios Exarchakis, Louis Thiry, Vincent Lostanlen, Joakim Andén, Tomás Angles, Gabriel Huang, Roberto Leonarduzzi
Author-email: edouard.oyallon@lip6.fr, belilove@iro.umontreal.ca, sergey.zagoruyko@inria.fr, michael.eickenberg@flatironinstitute.org, mathieu.andreux@ens.fr, georgios.exarchakis@ens.fr, louis.thiry@ens.fr, vincent.lostanlen@nyu.edu, janden@kth.se, tomas.angles@ens.fr, gabriel.huang@umontreal.ca, roberto.leonarduzzi@ens.fr
License: BSD-3-Clause
Download-URL: https://github.com/kymatio/kymatio/releases
Project-URL: Documentation, https://www.kymat.io/codereference.html
Project-URL: Source, https://github.com/kymatio/kymatio/
Project-URL: Tracker, https://github.com/kymatio/kymatio/issues
Project-URL: Authors, https://github.com/kymatio/kymatio/blob/master/AUTHORS.md
Platform: UNKNOWN
Classifier: Intended Audience :: Education
Classifier: Intended Audience :: Science/Research
Classifier: License :: OSI Approved :: BSD License
Classifier: Natural Language :: English
Classifier: Operating System :: MacOS
Classifier: Operating System :: POSIX :: Linux
Classifier: Programming Language :: Python :: 3.6
Classifier: Programming Language :: Python :: 3.7
Classifier: Programming Language :: Python :: 3.8
Classifier: Topic :: Multimedia :: Graphics :: 3D Modeling
Classifier: Topic :: Multimedia :: Sound/Audio :: Analysis
Classifier: Topic :: Scientific/Engineering :: Artificial Intelligence
Classifier: Topic :: Scientific/Engineering :: Chemistry
Classifier: Topic :: Scientific/Engineering :: Image Recognition
Classifier: Topic :: Scientific/Engineering :: Information Analysis
Classifier: Topic :: Scientific/Engineering :: Mathematics
Classifier: Topic :: Scientific/Engineering :: Physics
Classifier: Topic :: Software Development :: Libraries :: Python Modules
Requires-Python: >=3.6
License-File: LICENSE.md
License-File: AUTHORS.md
Requires-Dist: appdirs
Requires-Dist: configparser
Requires-Dist: numpy
Requires-Dist: packaging
Requires-Dist: scipy
